kara_storage/__init__.py
kara_storage/__main__.py
kara_storage/version.py
kara_storage/abc/__init__.py
kara_storage/abc/dataset.py
kara_storage/abc/iter.py
kara_storage/abc/kara.py
kara_storage/abc/serializer.py
kara_storage/abc/storage.py
kara_storage/backend/__init__.py
kara_storage/backend/file.py
kara_storage/backend/http.py
kara_storage/backend/oss.py
kara_storage/cmd/__init__.py
kara_storage/cmd/bind/__init__.py
kara_storage/cmd/bind/obj.py
kara_storage/cmd/bind/row.py
kara_storage/cmd/funcs/__init__.py
kara_storage/cmd/funcs/obj.py
kara_storage/cmd/funcs/row.py
kara_storage/object/__init__.py
kara_storage/object/dataset.py
kara_storage/pytorch/__init__.py
kara_storage/pytorch/base.py
kara_storage/pytorch/iter.py
kara_storage/pytorch/shuffle.py
kara_storage/row/__init__.py
kara_storage/row/dataset.py
kara_storage/row/proxy.py
kara_storage/row/row.py
kara_storage/row/trunk.py
kara_storage/rpc/__init__.py
kara_storage/rpc/client.py
kara_storage/rpc/kara_storage_pb2.py
kara_storage/rpc/kara_storage_pb2_grpc.py
kara_storage/rpc/op.py
kara_storage/rpc/server.py
kara_storage/serialization/__init__.py
kara_storage/serialization/json.py
kara_storage/serialization/pickle.py
kara_storage/serialization/raw.py
kara_storage/storage/__init__.py
kara_storage/storage/base.py
kara_storage-2.1.5.data/scripts/kara_storage
kara_storage-2.1.5.dist-info/METADATA
kara_storage-2.1.5.dist-info/WHEEL
kara_storage-2.1.5.dist-info/top_level.txt
kara_storage-2.1.5.dist-info/RECORD
