Metadata-Version: 2.1
Name: kara-storage
Version: 2.1.5
Summary: Kara Storage SDK
Home-page: https://git.thunlp.vip/kara/kara-row-storage
Author: a710128
Author-email: qbjooo@qq.com
License: UNKNOWN
Platform: UNKNOWN
Classifier: Programming Language :: Python :: 3
Classifier: License :: OSI Approved :: MIT License
Classifier: Programming Language :: C++
Requires-Python: >=3.6
Requires-Dist: orjson
Requires-Dist: tqdm
Requires-Dist: blessed
Requires-Dist: grpcio
Requires-Dist: protobuf
